atksh_utils/__init__.py
atksh_utils/version.py
atksh_utils/basic/__init__.py
atksh_utils/basic/functools.py
atksh_utils/nlp/__init__.py
atksh_utils/nlp/str_kernel.py
atksh_utils/openai/__init__.py
atksh_utils/openai/api.py
atksh_utils/openai/askgpt.py
atksh_utils/openai/functional.py
atksh_utils/openai/history.py
atksh_utils/openai/prompt.py
atksh_utils/openai/token.py
atksh_utils/openai/tool.py
atksh_utils-0.9.15.dist-info/licenses/LICENSE
atksh_utils-0.9.15.dist-info/METADATA
atksh_utils-0.9.15.dist-info/WHEEL
atksh_utils-0.9.15.dist-info/entry_points.txt
atksh_utils-0.9.15.dist-info/top_level.txt
atksh_utils-0.9.15.dist-info/RECORD
