Metadata-Version: 2.4
Name: atksh-utils
Version: 0.9.15
Summary: atksh's utils
Home-page: https://github.com/atksh/atksh_utils
Author: atksh
License: MIT License
Requires-Python: >=3.7
License-File: LICENSE
Requires-Dist: openai~=1.60.0
Requires-Dist: requests<3.0.0,>=2.0.0
Requires-Dist: duckduckgo_search>=8.0.1
Requires-Dist: dill<0.4.0,>=0.3.7
Requires-Dist: numba<0.59.0,>=0.56.4
Requires-Dist: pylatexenc==2.10
Requires-Dist: scipy<2.0.0,>=1.9.0
Requires-Dist: sympy<2.0.0,>=1.9.0
Requires-Dist: soundfile<0.13.0,>=0.12.1
Requires-Dist: sounddevice<0.5.0,>=0.4.6
Requires-Dist: pypdf~=3.17.2
Requires-Dist: tiktoken~=0.7.0
Requires-Dist: backoff<3.0.0,>=2.2.1
Requires-Dist: latest-user-agents==0.0.4
Requires-Dist: json-repair~=0.30.0
Provides-Extra: dev
Requires-Dist: black~=23.0.0; extra == "dev"
Requires-Dist: pytest~=7.2.2; extra == "dev"
Requires-Dist: isort~=5.12.0; extra == "dev"
Requires-Dist: pre-commit~=3.2.2; extra == "dev"
Dynamic: license-file
